[{"type":"image","fullpath":"\/images\/mario.png","metadata":{"resolution":"1080","creator":"Mario"}},{"type":"image","fullpath":"\/images\/dbz.jpg","metadata":{"resolution":"1080","creator":"Trunks"}},{"type":"video","fullpath":"\/images\/cat.mov","metadata":{"resolution":"720"}},{"type":"audio","fullpath":"\/images\/song.m4a","metadata":{"runtime":"4.20","creator":"Test"}},{"type":"document","fullpath":"\/images\/text.txt","metadata":{"creator":"Computer"}},{"type":"image","fullpath":"\/images\/SSJ3.png","metadata":{"resolution":"1080","creator":"Henry"}}]